odoo8_addon_pos_store_draft_order-8.0.1.0.0-py2.7-nspkg.pth
odoo8_addon_pos_store_draft_order-8.0.1.0.0.dist-info/DESCRIPTION.rst
odoo8_addon_pos_store_draft_order-8.0.1.0.0.dist-info/METADATA
odoo8_addon_pos_store_draft_order-8.0.1.0.0.dist-info/RECORD
odoo8_addon_pos_store_draft_order-8.0.1.0.0.dist-info/WHEEL
odoo8_addon_pos_store_draft_order-8.0.1.0.0.dist-info/metadata.json
odoo8_addon_pos_store_draft_order-8.0.1.0.0.dist-info/namespace_packages.txt
odoo8_addon_pos_store_draft_order-8.0.1.0.0.dist-info/top_level.txt
odoo_addons/pos_store_draft_order/README.rst
odoo_addons/pos_store_draft_order/__init__.py
odoo_addons/pos_store_draft_order/__openerp__.py
odoo_addons/pos_store_draft_order/demo/pos_config.yml
odoo_addons/pos_store_draft_order/i18n/fr.po
odoo_addons/pos_store_draft_order/i18n/pos_store_draft_order.pot
odoo_addons/pos_store_draft_order/model/__init__.py
odoo_addons/pos_store_draft_order/model/pos_config.py
odoo_addons/pos_store_draft_order/model/pos_order.py
odoo_addons/pos_store_draft_order/model/pos_session.py
odoo_addons/pos_store_draft_order/static/description/1_before_closing.png
odoo_addons/pos_store_draft_order/static/description/2_after_closing.png
odoo_addons/pos_store_draft_order/static/description/3_after_opening.png
odoo_addons/pos_store_draft_order/static/description/icon.png
odoo_addons/pos_store_draft_order/static/description/pos_order_states.png
odoo_addons/pos_store_draft_order/tests/__init__.py
odoo_addons/pos_store_draft_order/tests/test_pos_store_draft_order.py
odoo_addons/pos_store_draft_order/view/view.xml
