Metadata-Version: 2.0
Name: odoo8-addon-pos-store-draft-order
Version: 8.0.1.0.0
Summary: Allow users to close session with Draft Orders
Home-page: http://www.odoo-community.org
Author: GRAP,Odoo Community Association (OCA)
Author-email: support@odoo-community.org
License: AGPL-3
Platform: UNKNOWN
Classifier: Programming Language :: Python :: 2.7
Classifier: Framework :: Odoo
Classifier: License :: OSI Approved :: GNU Affero General Public License v3
Requires-Dist: odoo (<9.0a,>=8.0a)
